[
  {
    "product_id": "prod_001",
    "variant_id": "variant_001",
    "seller_id": "seller_002",
    "title": "Stainless Steel Water Bottle 1L",
    "description": "Insulated vacuum flask, keeps drinks cold 24 hours.",
    "category": "bottle",
    "price": 16.9,
    "currency": "SGD",
    "availability": "in_stock",
    "country": "Singapore",
    "city": "Singapore",
    "delivery_starts_at": "2026-06-07T09:00:00+08:00",
    "delivery_ends_at": "2026-06-09T18:00:00+08:00",
    "halal_status": "not_required",
    "halal_certifier": null,
    "halal_certificate_id": null,
    "halal_expires_at": null,
    "bpom_status": "not_required",
    "bpom_registration_number": null,
    "bpom_expires_at": null,
    "cod_available": true,
    "cod_max_amount": 500,
    "cod_supported_cities": ["Singapore"],
    "cod_requires_buyer_confirmation": true,
    "bnpl_available": true,
    "bnpl_provider": "SPayLater",
    "return_window_days": 15,
    "image_url": "/images/products/prod_001.jpg",
    "rating": 4.8,
    "sold_count": 12400,
    "discount_pct": 15
  },
  {
    "product_id": "prod_002",
    "variant_id": "variant_002",
    "seller_id": "seller_001",
    "title": "Halal Glow Serum Bottle 30ml",
    "description": "Brightening serum in travel-friendly glass bottle.",
    "category": "bottle",
    "price": 125000,
    "currency": "IDR",
    "availability": "in_stock",
    "country": "Indonesia",
    "city": "Jakarta",
    "delivery_starts_at": "2026-06-07T09:00:00+07:00",
    "delivery_ends_at": "2026-06-10T18:00:00+07:00",
    "halal_status": "certified",
    "halal_certifier": "LPPOM MUI",
    "halal_certificate_id": "HALAL-ID-001",
    "halal_expires_at": "2027-12-31",
    "bpom_status": "registered",
    "bpom_registration_number": "NA18240100001",
    "bpom_expires_at": "2028-04-30",
    "cod_available": true,
    "cod_max_amount": 500000,
    "cod_supported_cities": ["Jakarta"],
    "cod_requires_buyer_confirmation": true,
    "bnpl_available": true,
    "bnpl_provider": "SEA PayLater Stub",
    "return_window_days": 7,
    "image_url": "/images/products/prod_002.jpg",
    "rating": 4.7,
    "sold_count": 18100,
    "discount_pct": 20
  },
  {
    "product_id": "prod_003",
    "variant_id": "variant_003",
    "seller_id": "seller_002",
    "title": "COSRX Cleanser Pump Bottle 150ml",
    "description": "Low pH morning gel cleanser with pump dispenser.",
    "category": "bottle",
    "price": 12.9,
    "currency": "SGD",
    "availability": "in_stock",
    "country": "Singapore",
    "city": "Singapore",
    "delivery_starts_at": "2026-06-07T09:00:00+08:00",
    "delivery_ends_at": "2026-06-10T18:00:00+08:00",
    "halal_status": "unknown",
    "halal_certifier": null,
    "halal_certificate_id": null,
    "halal_expires_at": null,
    "bpom_status": "not_required",
    "bpom_registration_number": null,
    "bpom_expires_at": null,
    "cod_available": true,
    "cod_max_amount": 500,
    "cod_supported_cities": ["Singapore"],
    "cod_requires_buyer_confirmation": true,
    "bnpl_available": false,
    "bnpl_provider": null,
    "return_window_days": 15,
    "image_url": "/images/products/prod_003.jpg",
    "rating": 4.9,
    "sold_count": 22000,
    "discount_pct": 10
  },
  {
    "product_id": "prod_006",
    "variant_id": "variant_006",
    "seller_id": "seller_002",
    "title": "Men Cotton Polo T-Shirt",
    "description": "Breathable classic-fit polo in navy and white.",
    "category": "tshirt",
    "price": 19.9,
    "currency": "SGD",
    "availability": "in_stock",
    "country": "Singapore",
    "city": "Singapore",
    "delivery_starts_at": "2026-06-07T09:00:00+08:00",
    "delivery_ends_at": "2026-06-10T18:00:00+08:00",
    "halal_status": "not_required",
    "halal_certifier": null,
    "halal_certificate_id": null,
    "halal_expires_at": null,
    "bpom_status": "not_required",
    "bpom_registration_number": null,
    "bpom_expires_at": null,
    "cod_available": true,
    "cod_max_amount": 500,
    "cod_supported_cities": ["Singapore"],
    "cod_requires_buyer_confirmation": true,
    "bnpl_available": true,
    "bnpl_provider": "SPayLater",
    "return_window_days": 15,
    "image_url": "/images/products/prod_006.jpg",
    "rating": 4.7,
    "sold_count": 5400,
    "discount_pct": 30
  },
  {
    "product_id": "prod_007",
    "variant_id": "variant_007",
    "seller_id": "seller_002",
    "title": "Women Linen T-Shirt Dress",
    "description": "Oversized casual summer tee dress, beige.",
    "category": "tshirt",
    "price": 24.9,
    "currency": "SGD",
    "availability": "in_stock",
    "country": "Singapore",
    "city": "Singapore",
    "delivery_starts_at": "2026-06-07T09:00:00+08:00",
    "delivery_ends_at": "2026-06-10T18:00:00+08:00",
    "halal_status": "not_required",
    "halal_certifier": null,
    "halal_certificate_id": null,
    "halal_expires_at": null,
    "bpom_status": "not_required",
    "bpom_registration_number": null,
    "bpom_expires_at": null,
    "cod_available": true,
    "cod_max_amount": 500,
    "cod_supported_cities": ["Singapore"],
    "cod_requires_buyer_confirmation": true,
    "bnpl_available": true,
    "bnpl_provider": "SPayLater",
    "return_window_days": 15,
    "image_url": "/images/products/prod_007.jpg",
    "rating": 4.8,
    "sold_count": 3100,
    "discount_pct": 20
  },
  {
    "product_id": "prod_008",
    "variant_id": "variant_008",
    "seller_id": "seller_004",
    "title": "Unisex Graphic T-Shirt Pack",
    "description": "Soft cotton crew-neck tees, pack of 2.",
    "category": "tshirt",
    "price": 349,
    "currency": "PHP",
    "availability": "in_stock",
    "country": "Philippines",
    "city": "Manila",
    "delivery_starts_at": "2026-06-08T09:00:00+08:00",
    "delivery_ends_at": "2026-06-11T18:00:00+08:00",
    "halal_status": "not_required",
    "halal_certifier": null,
    "halal_certificate_id": null,
    "halal_expires_at": null,
    "bpom_status": "not_required",
    "bpom_registration_number": null,
    "bpom_expires_at": null,
    "cod_available": true,
    "cod_max_amount": 2000,
    "cod_supported_cities": ["Manila"],
    "cod_requires_buyer_confirmation": true,
    "bnpl_available": false,
    "bnpl_provider": null,
    "return_window_days": 7,
    "image_url": "/images/products/prod_008.jpg",
    "rating": 4.4,
    "sold_count": 9800,
    "discount_pct": 15
  },
  {
    "product_id": "prod_011",
    "variant_id": "variant_011",
    "seller_id": "seller_002",
    "title": "iPhone 16 Pro Silicone Case",
    "description": "Shockproof clear bumper case with MagSafe ring.",
    "category": "phone_case",
    "price": 5.9,
    "currency": "SGD",
    "availability": "in_stock",
    "country": "Singapore",
    "city": "Singapore",
    "delivery_starts_at": "2026-06-07T09:00:00+08:00",
    "delivery_ends_at": "2026-06-08T18:00:00+08:00",
    "halal_status": "not_required",
    "halal_certifier": null,
    "halal_certificate_id": null,
    "halal_expires_at": null,
    "bpom_status": "not_required",
    "bpom_registration_number": null,
    "bpom_expires_at": null,
    "cod_available": true,
    "cod_max_amount": 500,
    "cod_supported_cities": ["Singapore"],
    "cod_requires_buyer_confirmation": true,
    "bnpl_available": false,
    "bnpl_provider": null,
    "return_window_days": 15,
    "image_url": "/images/products/prod_011.jpg",
    "rating": 4.8,
    "sold_count": 37000,
    "discount_pct": 40
  },
  {
    "product_id": "prod_012",
    "variant_id": "variant_012",
    "seller_id": "seller_002",
    "title": "iPhone Tempered Glass Screen Protector",
    "description": "9H hardness full-cover glass protector 2-pack.",
    "category": "phone_case",
    "price": 3.9,
    "currency": "SGD",
    "availability": "in_stock",
    "country": "Singapore",
    "city": "Singapore",
    "delivery_starts_at": "2026-06-07T09:00:00+08:00",
    "delivery_ends_at": "2026-06-08T18:00:00+08:00",
    "halal_status": "not_required",
    "halal_certifier": null,
    "halal_certificate_id": null,
    "halal_expires_at": null,
    "bpom_status": "not_required",
    "bpom_registration_number": null,
    "bpom_expires_at": null,
    "cod_available": true,
    "cod_max_amount": 500,
    "cod_supported_cities": ["Singapore"],
    "cod_requires_buyer_confirmation": true,
    "bnpl_available": false,
    "bnpl_provider": null,
    "return_window_days": 15,
    "image_url": "/images/products/prod_012.jpg",
    "rating": 4.7,
    "sold_count": 26000,
    "discount_pct": 50
  },
  {
    "product_id": "prod_013",
    "variant_id": "variant_013",
    "seller_id": "seller_003",
    "title": "Samsung S24 Ultra Leather Case",
    "description": "Slim faux-leather case with card slot.",
    "category": "phone_case",
    "price": 18.9,
    "currency": "MYR",
    "availability": "in_stock",
    "country": "Malaysia",
    "city": "Kuala Lumpur",
    "delivery_starts_at": "2026-06-08T09:00:00+08:00",
    "delivery_ends_at": "2026-06-10T18:00:00+08:00",
    "halal_status": "not_required",
    "halal_certifier": null,
    "halal_certificate_id": null,
    "halal_expires_at": null,
    "bpom_status": "not_required",
    "bpom_registration_number": null,
    "bpom_expires_at": null,
    "cod_available": true,
    "cod_max_amount": 300,
    "cod_supported_cities": ["Kuala Lumpur"],
    "cod_requires_buyer_confirmation": true,
    "bnpl_available": true,
    "bnpl_provider": "SPayLater",
    "return_window_days": 7,
    "image_url": "/images/products/prod_013.jpg",
    "rating": 4.5,
    "sold_count": 4100,
    "discount_pct": 20
  },
  {
    "product_id": "prod_016",
    "variant_id": "variant_016",
    "seller_id": "seller_001",
    "title": "Halal Chicken Nuggets 1kg",
    "description": "Frozen breaded nuggets, MUI halal certified, family pack.",
    "category": "food_groceries",
    "price": 89000,
    "currency": "IDR",
    "availability": "in_stock",
    "country": "Indonesia",
    "city": "Jakarta",
    "delivery_starts_at": "2026-06-07T09:00:00+07:00",
    "delivery_ends_at": "2026-06-09T18:00:00+07:00",
    "halal_status": "certified",
    "halal_certifier": "LPPOM MUI",
    "halal_certificate_id": "HALAL-ID-016",
    "halal_expires_at": "2027-08-31",
    "bpom_status": "registered",
    "bpom_registration_number": "NA18240612016",
    "bpom_expires_at": "2028-06-30",
    "cod_available": true,
    "cod_max_amount": 500000,
    "cod_supported_cities": ["Jakarta"],
    "cod_requires_buyer_confirmation": true,
    "bnpl_available": false,
    "bnpl_provider": null,
    "return_window_days": 3,
    "image_url": "/images/products/prod_016.jpg",
    "rating": 4.6,
    "sold_count": 15200,
    "discount_pct": 12
  },
  {
    "product_id": "prod_017",
    "variant_id": "variant_017",
    "seller_id": "seller_001",
    "title": "Indomie Goreng Instant Noodles 5-pack",
    "description": "Classic fried noodle flavor bundle, quick pantry staple.",
    "category": "food_groceries",
    "price": 22500,
    "currency": "IDR",
    "availability": "in_stock",
    "country": "Indonesia",
    "city": "Jakarta",
    "delivery_starts_at": "2026-06-07T09:00:00+07:00",
    "delivery_ends_at": "2026-06-08T18:00:00+07:00",
    "halal_status": "certified",
    "halal_certifier": "LPPOM MUI",
    "halal_certificate_id": "HALAL-ID-017",
    "halal_expires_at": "2027-12-31",
    "bpom_status": "registered",
    "bpom_registration_number": "NA18240117017",
    "bpom_expires_at": "2028-12-31",
    "cod_available": true,
    "cod_max_amount": 500000,
    "cod_supported_cities": ["Jakarta"],
    "cod_requires_buyer_confirmation": true,
    "bnpl_available": false,
    "bnpl_provider": null,
    "return_window_days": 3,
    "image_url": "/images/products/prod_017.jpg",
    "rating": 4.9,
    "sold_count": 48000,
    "discount_pct": 5
  },
  {
    "product_id": "prod_018",
    "variant_id": "variant_018",
    "seller_id": "seller_002",
    "title": "Belgian Chocolate Cookies 400g",
    "description": "Crunchy cocoa cookies with chocolate chips, snack tin.",
    "category": "food_groceries",
    "price": 6.5,
    "currency": "SGD",
    "availability": "in_stock",
    "country": "Singapore",
    "city": "Singapore",
    "delivery_starts_at": "2026-06-07T09:00:00+08:00",
    "delivery_ends_at": "2026-06-09T18:00:00+08:00",
    "halal_status": "not_required",
    "halal_certifier": null,
    "halal_certificate_id": null,
    "halal_expires_at": null,
    "bpom_status": "not_required",
    "bpom_registration_number": null,
    "bpom_expires_at": null,
    "cod_available": true,
    "cod_max_amount": 500,
    "cod_supported_cities": ["Singapore"],
    "cod_requires_buyer_confirmation": true,
    "bnpl_available": true,
    "bnpl_provider": "SPayLater",
    "return_window_days": 7,
    "image_url": "/images/products/prod_018.jpg",
    "rating": 4.5,
    "sold_count": 11300,
    "discount_pct": 18
  },
  {
    "product_id": "prod_019",
    "variant_id": "variant_019",
    "seller_id": "seller_001",
    "title": "Matte Ruby Lipstick",
    "description": "Long-wear matte lipstick, BPOM registered, halal certified.",
    "category": "beauty_personal_care",
    "price": 145000,
    "currency": "IDR",
    "availability": "in_stock",
    "country": "Indonesia",
    "city": "Jakarta",
    "delivery_starts_at": "2026-06-07T09:00:00+07:00",
    "delivery_ends_at": "2026-06-10T18:00:00+07:00",
    "halal_status": "certified",
    "halal_certifier": "LPPOM MUI",
    "halal_certificate_id": "HALAL-ID-019",
    "halal_expires_at": "2027-11-30",
    "bpom_status": "registered",
    "bpom_registration_number": "NA18240119019",
    "bpom_expires_at": "2028-11-30",
    "cod_available": true,
    "cod_max_amount": 500000,
    "cod_supported_cities": ["Jakarta"],
    "cod_requires_buyer_confirmation": true,
    "bnpl_available": true,
    "bnpl_provider": "SEA PayLater Stub",
    "return_window_days": 7,
    "image_url": "/images/products/prod_019.jpg",
    "rating": 4.8,
    "sold_count": 9200,
    "discount_pct": 25
  },
  {
    "product_id": "prod_020",
    "variant_id": "variant_020",
    "seller_id": "seller_003",
    "title": "Vitamin C Brightening Serum 30ml",
    "description": "Daily antioxidant serum for dull skin, lightweight texture.",
    "category": "beauty_personal_care",
    "price": 42.9,
    "currency": "MYR",
    "availability": "in_stock",
    "country": "Malaysia",
    "city": "Kuala Lumpur",
    "delivery_starts_at": "2026-06-08T09:00:00+08:00",
    "delivery_ends_at": "2026-06-11T18:00:00+08:00",
    "halal_status": "certified",
    "halal_certifier": "JAKIM",
    "halal_certificate_id": "HALAL-MY-020",
    "halal_expires_at": "2027-06-30",
    "bpom_status": "not_required",
    "bpom_registration_number": null,
    "bpom_expires_at": null,
    "cod_available": true,
    "cod_max_amount": 300,
    "cod_supported_cities": ["Kuala Lumpur"],
    "cod_requires_buyer_confirmation": true,
    "bnpl_available": true,
    "bnpl_provider": "SPayLater",
    "return_window_days": 7,
    "image_url": "/images/products/prod_020.jpg",
    "rating": 4.7,
    "sold_count": 6400,
    "discount_pct": 15
  },
  {
    "product_id": "prod_021",
    "variant_id": "variant_021",
    "seller_id": "seller_005",
    "title": "Ginseng Repair Shampoo 400ml",
    "description": "Sulfate-free herbal shampoo for dry damaged hair.",
    "category": "beauty_personal_care",
    "price": 289,
    "currency": "THB",
    "availability": "in_stock",
    "country": "Thailand",
    "city": "Bangkok",
    "delivery_starts_at": "2026-06-07T09:00:00+07:00",
    "delivery_ends_at": "2026-06-09T18:00:00+07:00",
    "halal_status": "not_required",
    "halal_certifier": null,
    "halal_certificate_id": null,
    "halal_expires_at": null,
    "bpom_status": "not_required",
    "bpom_registration_number": null,
    "bpom_expires_at": null,
    "cod_available": true,
    "cod_max_amount": 1500,
    "cod_supported_cities": ["Bangkok"],
    "cod_requires_buyer_confirmation": true,
    "bnpl_available": true,
    "bnpl_provider": "SPayLater",
    "return_window_days": 7,
    "image_url": "/images/products/prod_021.jpg",
    "rating": 4.6,
    "sold_count": 7800,
    "discount_pct": 10
  }
]
